hkopenai_common/__init__.py
hkopenai_common/cli_utils.py
hkopenai_common/csv_utils.py
hkopenai_common/json_utils.py
hkopenai_common/xml_utils.py
hkopenai_common-0.4.0.dist-info/METADATA
hkopenai_common-0.4.0.dist-info/WHEEL
hkopenai_common-0.4.0.dist-info/top_level.txt
hkopenai_common-0.4.0.dist-info/RECORD
