Metadata-Version: 2.4
Name: hkopenai_common
Version: 0.4.0
Summary: Common utilities for HK OpenAI MCP Servers
Author-email: Neo Chow <neo@01man.com>
Project-URL: Homepage, https://github.com/hkopenai/hkopenai_common
Project-URL: Bug Tracker, https://github.com/hkopenai/hkopenai_common/issues
Keywords: mcp,server,utilities
Classifier: Programming Language :: Python :: 3
Classifier: License :: OSI Approved :: MIT License
Classifier: Operating System :: OS Independent
Requires-Python: >=3.9
Requires-Dist: pytest>=8.2.0
Requires-Dist: pytest-cov>=6.1.1
Requires-Dist: requests>=2.31.0
Provides-Extra: dev
Requires-Dist: pytest>=7.0; extra == "dev"
Requires-Dist: pytest-mock; extra == "dev"
